sceneid/__init__.py
sceneid/apps.py
sceneid/client.py
sceneid/forms.py
sceneid/models.py
sceneid/urls.py
sceneid/views.py
sceneid/migrations/0001_initial.py
sceneid/migrations/__init__.py
sceneid/static/sceneid/images/login-large.png
sceneid/static/sceneid/images/login-small.png
sceneid/templates/sceneid/connect.html
sceneid/templates/sceneid/tags/login_button_large.html
sceneid/templates/sceneid/tags/login_button_small.html
sceneid/templatetags/__init__.py
sceneid/templatetags/sceneid_tags.py
django_sceneid-0.1.2.dist-info/LICENSE
django_sceneid-0.1.2.dist-info/METADATA
django_sceneid-0.1.2.dist-info/WHEEL
django_sceneid-0.1.2.dist-info/top_level.txt
django_sceneid-0.1.2.dist-info/RECORD
