Metadata-Version: 2.1
Name: django-sceneid
Version: 0.1.2
Summary: SceneID authentication for Django
Home-page: https://github.com/demozoo/django-sceneid/
Author: Matt Westcott
Author-email: matt@west.co.tt
License: BSD
Platform: UNKNOWN
Classifier: Development Status :: 3 - Alpha
Classifier: Environment :: Web Environment
Classifier: Intended Audience :: Developers
Classifier: Programming Language :: Python :: 3
Classifier: Framework :: Django :: 3.0
Classifier: Framework :: Django :: 3.1
Classifier: Framework :: Django :: 3.2
Classifier: Framework :: Django :: 4.0
Classifier: Framework :: Django :: 4.1
Classifier: Framework :: Django :: 4.2
Classifier: Framework :: Django :: 5.0
Classifier: Topic :: Internet :: WWW/HTTP
Classifier: License :: OSI Approved :: BSD License
Classifier: Operating System :: OS Independent
Requires-Python: >=3.6
Requires-Dist: Django (>=3.0)
Requires-Dist: requests (<3,>=2)
Provides-Extra: testing
Requires-Dist: responses (<0.21,>=0.14) ; extra == 'testing'
